donzo_plus_adv/__init__.py
donzo_plus_adv/plus.py
donzo_plus_adv-0.1.0.dist-info/METADATA
donzo_plus_adv-0.1.0.dist-info/WHEEL
donzo_plus_adv-0.1.0.dist-info/entry_points.txt
donzo_plus_adv-0.1.0.dist-info/top_level.txt
donzo_plus_adv-0.1.0.dist-info/RECORD
